pyboot/commons/pybatis/__init__.py
pyboot/commons/pybatis/pybatis.py
pyboot/commons/pybatis/pydbc.py
pyboot_commons_pybatis-1.3.3.dist-info/licenses/LICENSE
pyboot_commons_pybatis-1.3.3.dist-info/METADATA
pyboot_commons_pybatis-1.3.3.dist-info/WHEEL
pyboot_commons_pybatis-1.3.3.dist-info/top_level.txt
pyboot_commons_pybatis-1.3.3.dist-info/RECORD
