Metadata-Version: 2.4
Name: pyboot-commons-pybatis
Version: 1.3.3
Summary: Pyboot-commons-pybatis is an open-source Pyboot utility package that A Python-extended PyBatis component that integrates ORM database operations similar to Spring MyBatis-Plus, enabling out-of-the-box CRUD and advanced querying capabilities.
Author-email: joinsunsoft <793875613@qq.com>
Maintainer-email: joinsunsoft <inthirties.liu@hotmail.com>
License-Expression: Apache-2.0
Project-URL: Homepage, https://gitee.com/pyboot/commons-pybatis
Project-URL: Repository, https://gitee.com/pyboot/commons-pybatis
Project-URL: Issues, https://gitee.com/pyboot/commons-pybatis
Keywords: web,framework,cli,springboot,fastapi,mybatis,pybatis,jdbc,pydbc,database
Classifier: Development Status :: 4 - Beta
Classifier: Intended Audience :: Developers
Classifier: Operating System :: OS Independent
Classifier: Programming Language :: Python :: 3
Classifier: Programming Language :: Python :: 3.8
Classifier: Programming Language :: Python :: 3.9
Classifier: Programming Language :: Python :: 3.10
Classifier: Programming Language :: Python :: 3.11
Classifier: Programming Language :: Python :: 3.12
Classifier: Topic :: Software Development :: Libraries :: Application Frameworks
Requires-Python: >=3.12.10
License-File: LICENSE
Requires-Dist: cachetools==5.5.0
Requires-Dist: dbutils==3.1.1
Requires-Dist: Jinja2==3.1.6
Requires-Dist: pyboot-commons-utils>=1.0.0
Requires-Dist: SQLAlchemy==2.0.44
Dynamic: license-file
